health/__about__.py
health/__init__.py
health/monitor.py
icpsr_health-1.0.0.dist-info/METADATA
icpsr_health-1.0.0.dist-info/WHEEL
icpsr_health-1.0.0.dist-info/RECORD
