Metadata-Version: 2.3
Name: ICPSR.health
Version: 1.0.0
Summary: Library for monitoring the readiness of a service and its dependencies.
Project-URL: Documentation, https://gitlab.icpsr.umich.edu/icpsr/dev/data-engineering/libraries/health-monitor#readme
Project-URL: Issues, https://gitlab.icpsr.umich.edu/icpsr/dev/data-engineering/libraries/health-monitor/issues
Project-URL: Source, https://gitlab.icpsr.umich.edu/icpsr/dev/data-engineering/libraries/health-monitor
Author-email: Faelin Landy <faelin@umich.edu>
License-Expression: Apache-2.0
Classifier: Development Status :: 4 - Beta
Classifier: Intended Audience :: Developers
Classifier: License :: OSI Approved :: Apache Software License
Classifier: Programming Language :: Python
Classifier: Programming Language :: Python :: 3.7
Classifier: Programming Language :: Python :: 3.8
Classifier: Programming Language :: Python :: 3.9
Classifier: Programming Language :: Python :: 3.10
Classifier: Programming Language :: Python :: 3.11
Classifier: Programming Language :: Python :: 3.12
Classifier: Programming Language :: Python :: Implementation :: CPython
Classifier: Programming Language :: Python :: Implementation :: PyPy
Classifier: Topic :: System :: Monitoring
Requires-Python: >=3.7
